{
  "box-model.padding-block-start": {
    "resolvesTo": "semantic.input.size.medium.padding-block",
    "fallback": "8px",
    "layer": "semantic"
  },
  "box-model.padding-block-end": {
    "resolvesTo": "semantic.input.size.medium.padding-block",
    "fallback": "8px",
    "layer": "semantic"
  },
  "box-model.padding-inline-start": {
    "resolvesTo": "semantic.input.size.medium.padding-inline",
    "fallback": "12px",
    "layer": "semantic"
  },
  "box-model.padding-inline-end": {
    "resolvesTo": "semantic.input.size.medium.padding-inline",
    "fallback": "12px",
    "layer": "semantic"
  },
  "box-model.gap": {
    "resolvesTo": "semantic.input.size.medium.gap",
    "fallback": "8px",
    "layer": "semantic"
  },
  "box-model.min-height": {
    "resolvesTo": "semantic.input.size.medium.min-height",
    "fallback": "36px",
    "layer": "semantic"
  },
  "select.color.background.default": {
    "resolvesTo": "semantic.color.background.primary",
    "fallback": "#ffffff",
    "layer": "semantic"
  },
  "select.color.foreground.default": {
    "resolvesTo": "semantic.color.foreground.primary",
    "fallback": "#141414",
    "layer": "semantic"
  },
  "select.color.border.default": {
    "resolvesTo": "semantic.color.border.primary",
    "fallback": "#f29495",
    "layer": "semantic"
  },
  "select.color.icon.default": {
    "resolvesTo": "semantic.color.foreground.secondary",
    "fallback": "#555555",
    "layer": "semantic"
  },
  "select.color.placeholder.default": {
    "resolvesTo": "semantic.color.foreground.placeholder",
    "fallback": "#8f8f8f",
    "layer": "semantic"
  },
  "select.size.padding.default": {
    "resolvesTo": "core.spacing.size.03",
    "fallback": "4px",
    "layer": "core"
  },
  "select.size.radius.default": {
    "resolvesTo": "core.shape.radius.medium",
    "fallback": "8px",
    "layer": "core"
  },
  "select.size.border.default": {
    "resolvesTo": "core.shape.border.width.hairline",
    "fallback": "1px",
    "layer": "core"
  },
  "select.size.sm.height": {
    "resolvesTo": "semantic.control.size.sm.height",
    "fallback": "24px",
    "layer": "semantic"
  },
  "select.size.md.height": {
    "resolvesTo": "semantic.control.size.md.height",
    "fallback": "32px",
    "layer": "semantic"
  },
  "select.size.lg.height": {
    "resolvesTo": "semantic.control.size.lg.height",
    "fallback": "48px",
    "layer": "semantic"
  },
  "select.font.size.default": {
    "resolvesTo": "semantic.typography.body.02",
    "fallback": "16px",
    "layer": "semantic"
  },
  "select.font.lineHeight.default": {
    "resolvesTo": "semantic.typography.line.height.body",
    "fallback": "1.5",
    "layer": "semantic"
  },
  "select.color.icon.isOpen": {
    "resolvesTo": "semantic.color.foreground.accent",
    "fallback": "#d9292b",
    "layer": "semantic"
  },
  "select.focus.ring.width": {
    "resolvesTo": "semantic.focus.ring.width",
    "fallback": "2px",
    "layer": "semantic"
  },
  "select.focus.ring.color": {
    "resolvesTo": "semantic.focus.ring.color",
    "fallback": "#0a65fe",
    "layer": "semantic"
  },
  "select.focus.ring.style": {
    "resolvesTo": "semantic.focus.ring.style",
    "fallback": "solid",
    "layer": "semantic"
  },
  "select.focus.ring.offset": {
    "resolvesTo": "semantic.focus.ring.offset",
    "fallback": "2px",
    "layer": "semantic"
  }
}
